setup.py
checkpoints/__init__.py
checkpoints/checkpoints.py
checkpoints.egg-info/PKG-INFO
checkpoints.egg-info/SOURCES.txt
checkpoints.egg-info/dependency_links.txt
checkpoints.egg-info/top_level.txt