Metadata-Version: 1.1
Name: checkpoints
Version: 0.0.1
Summary: Partial result caching for pandas in Python.
Home-page: https://github.com/ResidentMario/checkpoints
Author: Aleksey Bilogur
Author-email: aleksey.bilogur@residentmar.io
License: UNKNOWN
Download-URL: https://github.com/ResidentMario/checkpoints/tarball/0.0.1
Keywords: data,data analysis,exceptions,error handling,defensive programming,data science,pandas,python,jupyter
Platform: UNKNOWN
